dqm_ml_core/__init__.py
dqm_ml_core/_version_.py
dqm_ml_core/py.typed
dqm_ml_core/api/__init__.py
dqm_ml_core/api/data_processor.py
dqm_ml_core/metrics/__init__.py
dqm_ml_core/metrics/completeness.py
dqm_ml_core/metrics/representativeness.py
dqm_ml_core/utils/__init__.py
dqm_ml_core/utils/metric_runner.py
dqm_ml_core/utils/registry.py
dqm_ml_core-1.1.4.dist-info/METADATA
dqm_ml_core-1.1.4.dist-info/WHEEL
dqm_ml_core-1.1.4.dist-info/entry_points.txt
dqm_ml_core-1.1.4.dist-info/top_level.txt
dqm_ml_core-1.1.4.dist-info/RECORD
