Metadata-Version: 2.4
Name: dqm-ml-core
Version: 1.1.4
Summary: Python library designed provide core dqml metrics without huge dependencies, as well as common API shared by metrics
Author-email: Safenai <support@safenai.io>, IRT SystemX <support@irt-systemx.fr>
License-Expression: Apache-2.0
Project-URL: Homepage, https://irt-systemx.github.io/dqm-ml
Project-URL: Documentation, https://irt-systemx.github.io/dqm-ml
Project-URL: Repository, https://github.com/IRT-SystemX/dqm-ml
Keywords: ml,metrics,data
Classifier: Development Status :: 4 - Beta
Classifier: Intended Audience :: Developers
Classifier: Topic :: Software Development :: Libraries :: Python Modules
Classifier: Programming Language :: Python
Classifier: Programming Language :: Python :: 3.10
Classifier: Programming Language :: Python :: 3.11
Classifier: Programming Language :: Python :: 3.12
Classifier: Programming Language :: Python :: 3.13
Classifier: Typing :: Typed
Requires-Python: >=3.10
Requires-Dist: pyarrow>=6.0.0
Requires-Dist: numpy>=1.20.0
Requires-Dist: pandas>=1.3.0
Requires-Dist: scipy>=1.7.0
